is_string/__init__.py
is_string/is_string.py
is_string-0.0.8.dist-info/LICENSE
is_string-0.0.8.dist-info/METADATA
is_string-0.0.8.dist-info/WHEEL
is_string-0.0.8.dist-info/top_level.txt
is_string-0.0.8.dist-info/RECORD
