Metadata-Version: 2.1
Name: is-string
Version: 0.0.8
Summary: A small Python library to determine if something is a string
Home-page: https://github.com/przemo199/is-string
Author: Przemek Kaminski
Author-email: przemyslaw.m.kaminski@gmail.com
License: UNKNOWN
Keywords: python,str,string
Platform: UNKNOWN
Classifier: Programming Language :: Python :: 3
Classifier: License :: OSI Approved :: MIT License
Classifier: Operating System :: OS Independent
